crewaimaster/__init__.py
crewaimaster/cli.py
crewaimaster/agents/__init__.py
crewaimaster/agents/agent_designer_agent.py
crewaimaster/agents/crew_orchestrator_agent.py
crewaimaster/agents/custom_tool_generator_agent.py
crewaimaster/agents/task_analyzer_agent.py
crewaimaster/agents/tool_designer_agent.py
crewaimaster/core/__init__.py
crewaimaster/core/ai_tool_creator.py
crewaimaster/core/code_generator.py
crewaimaster/core/config.py
crewaimaster/core/crew_designer.py
crewaimaster/core/file_based_crew_designer.py
crewaimaster/core/file_generator.py
crewaimaster/core/intelligent_tool_creator.py
crewaimaster/core/llm_provider.py
crewaimaster/core/master_agent.py
crewaimaster/core/master_agent_crew.py
crewaimaster/core/master_agent_tools.py
crewaimaster/core/task_analyzer.py
crewaimaster/crews/__init__.py
crewaimaster/knowledge_base/__init__.py
crewaimaster/knowledge_base/knowledge_manager.py
crewaimaster/memory/__init__.py
crewaimaster/tools/__init__.py
crewaimaster/tools/guardrails.py
crewaimaster/tools/registry.py
crewaimaster/ui/__init__.py
crewaimaster-0.1.3.dist-info/licenses/LICENSE
crewaimaster-0.1.3.dist-info/METADATA
crewaimaster-0.1.3.dist-info/WHEEL
crewaimaster-0.1.3.dist-info/entry_points.txt
crewaimaster-0.1.3.dist-info/top_level.txt
crewaimaster-0.1.3.dist-info/RECORD
