Metadata-Version: 2.4
Name: crewaimaster
Version: 0.1.3
Summary: A Python package for building intelligent multi-agent systems using CrewAI
Author-email: Vishnu Prasad <vishnuprasadapp@gmail.com>
License: MIT
Project-URL: Homepage, https://github.com/VishApp/crewaimaster
Project-URL: Documentation, https://github.com/VishApp/crewaimaster#readme
Project-URL: Repository, https://github.com/VishApp/crewaimaster
Project-URL: Issues, https://github.com/VishApp/crewaimaster/issues
Project-URL: Changelog, https://github.com/VishApp/crewaimaster/blob/main/CHANGELOG.md
Keywords: ai,multi-agent,crewai,automation,agents
Classifier: Development Status :: 3 - Alpha
Classifier: Intended Audience :: Developers
Classifier: License :: OSI Approved :: MIT License
Classifier: Programming Language :: Python :: 3
Classifier: Programming Language :: Python :: 3.9
Classifier: Programming Language :: Python :: 3.10
Classifier: Programming Language :: Python :: 3.11
Classifier: Programming Language :: Python :: 3.12
Requires-Python: >=3.10
License-File: LICENSE
Requires-Dist: crewai
Requires-Dist: crewai-tools
Requires-Dist: pydantic
Requires-Dist: python-dotenv
Requires-Dist: rich
Requires-Dist: typer
Requires-Dist: openai
Requires-Dist: pyyaml
Requires-Dist: langchain-anthropic
Requires-Dist: langchain-google-genai
Requires-Dist: langchain-openai
Provides-Extra: dev
Requires-Dist: pytest>=7.0.0; extra == "dev"
Requires-Dist: pytest-asyncio>=0.21.0; extra == "dev"
Requires-Dist: black>=23.0.0; extra == "dev"
Requires-Dist: ruff>=0.1.0; extra == "dev"
Requires-Dist: mypy>=1.0.0; extra == "dev"
Requires-Dist: pre-commit>=3.0.0; extra == "dev"
Provides-Extra: web
Requires-Dist: fastapi>=0.100.0; extra == "web"
Requires-Dist: uvicorn>=0.23.0; extra == "web"
Requires-Dist: jinja2>=3.1.0; extra == "web"
Dynamic: license-file
